{"_id":"006","_add_time":1596416400000,"comment":"更细粒化的自定义角色权限示例","enable":true,"permission":[],"role_id":"custom-role-1","role_name":"自定义角色-1"}
{"_id":"004","_add_time":1596416400000,"comment":"系统内置角色 - 请勿修改","enable":true,"permission":[],"role_id":"admin-lv1","role_name":"初级管理员"}
{"_id":"003","_add_time":1596416400000,"comment":"系统内置角色 - 请勿修改","enable":true,"permission":[],"role_id":"admin-lv2","role_name":"中级管理员"}
{"_id":"005","_add_time":1596416400000,"comment":"系统内置角色 - 请勿修改","enable":true,"permission":[],"role_id":"query-all","role_name":"boss"}
{"_id":"001","_add_time":1596416400000,"comment":"系统内置角色 - 请勿修改","enable":true,"permission":[],"role_id":"admin","role_name":"超级管理员"}
{"_id":"002","_add_time":1596416400000,"comment":"系统内置角色 - 请勿修改","enable":true,"permission":[],"role_id":"admin-lv3","role_name":"高级管理员"}
